evermind/__init__.py
evermind/config.py
evermind/manager.py
evermind/models.py
evermind/protocols.py
evermind/task_queues/__init__.py
evermind/task_queues/in_process.py
evermind-0.1.0.dist-info/LICENSE
evermind-0.1.0.dist-info/METADATA
evermind-0.1.0.dist-info/WHEEL
evermind-0.1.0.dist-info/RECORD
