Metadata-Version: 2.3
Name: evermind
Version: 0.1.0
Summary: 为智能体打造的“神级记忆装备”，一个可实现永久存活与自我进化的认知核心。
License: Apache-2.0
Author: AlbertCui
Author-email: albertzhouzhou@gmail.com
Requires-Python: >=3.9,<4.0
Classifier: License :: OSI Approved :: Apache Software License
Classifier: Programming Language :: Python :: 3
Classifier: Programming Language :: Python :: 3.9
Classifier: Programming Language :: Python :: 3.10
Classifier: Programming Language :: Python :: 3.11
Classifier: Programming Language :: Python :: 3.12
Classifier: Programming Language :: Python :: 3.13
Requires-Dist: faiss-cpu (>=1.8.0,<2.0.0)
Requires-Dist: langchain-community (>=0.2.1,<0.3.0)
Requires-Dist: langchain-core (>=0.2.1,<0.3.0)
Requires-Dist: langchain-openai (>=0.1.7,<0.2.0)
Requires-Dist: numpy (>=1.26.4,<2.0.0)
Requires-Dist: pydantic (>=2.7.1,<3.0.0)
Requires-Dist: tiktoken (>=0.7.0,<0.8.0)
Project-URL: Repository, https://github.com/pforge-ai/evermind
